[
    {
        "chinese_name": [
            "黄",
            "焖",
            "鸡煲"
        ],
        "english_name": [
            "L12"
        ],
        "chinese_description": [],
        "english_description": []
    },
    {
        "chinese_name": [
            "干锅",
            "手撕",
            "包菜"
        ],
        "english_name": [
            "L13"
        ],
        "chinese_description": [],
        "english_description": []
    },
    {
        "chinese_name": [
            "啫",
            "啫",
            "海鳗",
            "煲"
        ],
        "english_name": [
            "with",
            "Pork"
        ],
        "chinese_description": [],
        "english_description": []
    },
    {
        "chinese_name": [
            "支",
            "竹",
            "羊",
            "腩",
            "煲"
        ],
        "english_name": [
            "L14"
        ],
        "chinese_description": [],
        "english_description": []
    },
    {
        "chinese_name": [
            "斑",
            "楠",
            "豆腐",
            "煲"
        ],
        "english_name": [
            "Conger",
            "Eel",
            "Hot",
            "Pot"
        ],
        "chinese_description": [],
        "english_description": [
            [
                "L19"
            ]
        ]
    },
    {
        "chinese_name": [
            "啫",
            "啫",
            "鸡煲"
        ],
        "english_name": [
            "L15"
        ],
        "chinese_description": [],
        "english_description": []
    },
    {
        "chinese_name": [
            "上",
            "汤",
            "野菌",
            "什",
            "菜",
            "煲"
        ],
        "english_name": [
            "Sizzling",
            "Chicken",
            "Hot",
            "Pot"
        ],
        "chinese_description": [],
        "english_description": []
    },
    {
        "chinese_name": [
            "咸鱼",
            "鸡",
            "茄子",
            "豆腐",
            "煲"
        ],
        "english_name": [
            "Wild",
            "Mushroom",
            "and",
            "Mixed"
        ],
        "chinese_description": [],
        "english_description": [
            [
                "Vegetable",
                "Hot",
                "Pot"
            ]
        ]
    }
]