[
    {
        "chinese_name": [
            "菜"
        ],
        "english_name": [
            "HOME",
            "TRADITIONAL"
        ],
        "chinese_description": [],
        "english_description": [
            [
                "COLD",
                "DISHES"
            ]
        ]
    },
    {
        "chinese_name": [
            "夫妻肺片"
        ],
        "english_name": [
            "K1"
        ],
        "chinese_description": [],
        "english_description": []
    },
    {
        "chinese_name": [
            "口水",
            "鸡"
        ],
        "english_name": [
            "K2"
        ],
        "chinese_description": [],
        "english_description": []
    },
    {
        "chinese_name": [
            "五香",
            "牛肉"
        ],
        "english_name": [
            "K3"
        ],
        "chinese_description": [],
        "english_description": []
    },
    {
        "chinese_name": [
            "麻辣",
            "牛肉"
        ],
        "english_name": [
            "Beef",
            "Shin",
            "with",
            "Five",
            "Spices"
        ],
        "chinese_description": [],
        "english_description": []
    },
    {
        "chinese_name": [
            "拍",
            "黄瓜"
        ],
        "english_name": [
            "Hot",
            "and",
            "Spicy",
            "Sliced",
            "Beef"
        ],
        "chinese_description": [],
        "english_description": [
            [
                "K5"
            ]
        ]
    },
    {
        "chinese_name": [
            "双",
            "椒",
            "木耳"
        ],
        "english_name": [
            "Smashed",
            "Cucumber",
            "V",
            "VG"
        ],
        "chinese_description": [],
        "english_description": []
    }
]