[
    {
        "chinese_name": [
            "铁板",
            "干锅",
            "煲仔"
        ],
        "english_name": [],
        "chinese_description": [],
        "english_description": []
    },
    {
        "chinese_name": [
            "干锅",
            "仔鸡"
        ],
        "english_name": [
            "L"
        ],
        "chinese_description": [],
        "english_description": []
    },
    {
        "chinese_name": [
            "干锅",
            "肥肠"
        ],
        "english_name": [
            "L7"
        ],
        "chinese_description": [],
        "english_description": []
    },
    {
        "chinese_name": [
            "香辣",
            "猪手",
            "煲"
        ],
        "english_name": [
            "Griddle",
            "Cooked",
            "Pork",
            "Intestine"
        ],
        "chinese_description": [],
        "english_description": []
    },
    {
        "chinese_name": [
            "铁板",
            "牛柳",
            "黑椒",
            "豉",
            "椒",
            "中式"
        ],
        "english_name": [
            "Griddle",
            "Cooked",
            "Chicken"
        ],
        "chinese_description": [],
        "english_description": [
            [
                "L2"
            ]
        ]
    },
    {
        "chinese_name": [
            "鱼香",
            "茄子",
            "煲"
        ],
        "english_name": [
            "Hot",
            "and",
            "Spicy",
            "Trotters",
            "on",
            "the",
            "Bone"
        ],
        "chinese_description": [],
        "english_description": []
    },
    {
        "chinese_name": [
            "铁板",
            "玉",
            "子",
            "豆腐"
        ],
        "english_name": [
            "Sizzling",
            "Fillet",
            "Steak",
            "in"
        ],
        "chinese_description": [],
        "english_description": [
            [
                "Black",
                "Pepper",
                "Black",
                "Bean",
                "Cantonese",
                "Style"
            ],
            [
                "L3"
            ]
        ]
    },
    {
        "chinese_name": [
            "肥肠",
            "火锅",
            "鱼"
        ],
        "english_name": [
            "Sizzling",
            "Egg",
            "Tofu",
            "with",
            "Pork"
        ],
        "chinese_description": [],
        "english_description": []
    },
    {
        "chinese_name": [
            "萝卜",
            "牛腩",
            "煲"
        ],
        "english_name": [
            "Spicy",
            "Aubergine",
            "with",
            "Minced"
        ],
        "chinese_description": [],
        "english_description": [
            [
                "Pork",
                "Hot",
                "Pot"
            ]
        ]
    },
    {
        "chinese_name": [
            "梅菜",
            "扣肉",
            "煲"
        ],
        "english_name": [
            "Hot",
            "and",
            "Spicy",
            "Fish",
            "Fillet",
            "with"
        ],
        "chinese_description": [],
        "english_description": [
            [
                "Beef",
                "Brisket",
                "with",
                "Mooli",
                "Hot",
                "Pot"
            ]
        ]
    },
    {
        "chinese_name": [
            "干锅",
            "鱿鱼",
            "须"
        ],
        "english_name": [
            "Hot",
            "and",
            "Spicy",
            "Fish",
            "Fillet",
            "with"
        ],
        "chinese_description": [],
        "english_description": [
            [
                "L5"
            ]
        ]
    },
    {
        "chinese_name": [
            "干锅",
            "香辣",
            "虾",
            "无",
            "克"
        ],
        "english_name": [
            "Griddle",
            "Cooked",
            "Squid",
            "Tentacles"
        ],
        "chinese_description": [],
        "english_description": [
            [
                "L6"
            ]
        ]
    }
]