[
    {
        "chinese_name": [
            "时价"
        ],
        "english_name": [],
        "chinese_description": [],
        "english_description": [],
        "raw_text": null
    },
    {
        "chinese_name": [
            "蒜蓉",
            "粉丝",
            "蒸",
            "带子",
            "酱",
            "蒜蓉",
            "蒸",
            "带子",
            "豉",
            "汁",
            "蒸",
            "带子"
        ],
        "english_name": [
            "XO",
            "minimum",
            "pieces"
        ],
        "chinese_description": [],
        "english_description": [
            [
                "Steamed",
                "scallop",
                "with",
                "garlic"
            ],
            [
                "and",
                "vermicelli",
                "in",
                "XOsauce"
            ],
            [
                "in",
                "black",
                "bean",
                "sauce"
            ],
            [
                "Market",
                "Price"
            ]
        ],
        "raw_text": null
    },
    {
        "chinese_name": [
            "蒜蓉",
            "粉丝",
            "蒸",
            "蛏",
            "子",
            "酱",
            "蒜蓉",
            "蒸",
            "蛏",
            "子",
            "豉",
            "汁",
            "蒸",
            "蛏",
            "子"
        ],
        "english_name": [
            "XO",
            "Steamed",
            "razor",
            "clams",
            "with",
            "garlic"
        ],
        "chinese_description": [],
        "english_description": [
            [
                "and",
                "vermicelli",
                "in",
                "XOsauce"
            ],
            [
                "in",
                "black",
                "bean",
                "sauce"
            ],
            [
                "minimum",
                "pieces"
            ],
            [
                "Market",
                "Price"
            ]
        ],
        "raw_text": null
    },
    {
        "chinese_name": [
            "时价"
        ],
        "english_name": [],
        "chinese_description": [],
        "english_description": [],
        "raw_text": null
    },
    {
        "chinese_name": [
            "时价"
        ],
        "english_name": [],
        "chinese_description": [],
        "english_description": [],
        "raw_text": null
    },
    {
        "chinese_name": [
            "蒜蓉",
            "粉丝",
            "蒸",
            "开",
            "边",
            "龙虾"
        ],
        "english_name": [
            "Steamed",
            "halve",
            "lobster",
            "in",
            "shell",
            "with",
            "vermicelli",
            "and",
            "fresh",
            "garlic"
        ],
        "chinese_description": [],
        "english_description": [],
        "raw_text": null
    },
    {
        "chinese_name": [
            "时价"
        ],
        "english_name": [],
        "chinese_description": [],
        "english_description": [],
        "raw_text": null
    },
    {
        "chinese_name": [
            "海"
        ],
        "english_name": [],
        "chinese_description": [],
        "english_description": [],
        "raw_text": null
    },
    {
        "chinese_name": [
            "蒜蓉",
            "粉丝",
            "蒸",
            "开",
            "边",
            "老虎",
            "虾"
        ],
        "english_name": [
            "Steamed",
            "tiger",
            "prawns",
            "in",
            "shell",
            "with",
            "vermicelli",
            "and",
            "fresh",
            "garlic"
        ],
        "chinese_description": [],
        "english_description": [],
        "raw_text": null
    },
    {
        "chinese_name": [
            "蒜蓉",
            "粉丝",
            "蒸",
            "开",
            "边",
            "大虾"
        ],
        "english_name": [
            "Steamed",
            "king",
            "prawn",
            "in",
            "shell",
            "with"
        ],
        "chinese_description": [],
        "english_description": [
            [
                "vermicelli",
                "and",
                "fresh",
                "garlic"
            ]
        ],
        "raw_text": null
    },
    {
        "chinese_name": [
            "金银",
            "蒜蓉",
            "蒸",
            "生蚝",
            "每只"
        ],
        "english_name": [
            "Steamed",
            "oyster",
            "with",
            "garlic",
            "sauce",
            "each"
        ],
        "chinese_description": [],
        "english_description": [],
        "raw_text": null
    },
    {
        "chinese_name": [
            "我们",
            "会",
            "加收",
            "服务",
            "费"
        ],
        "english_name": [
            "Wecharge",
            "a",
            "service",
            "charge",
            "on",
            "all",
            "customers"
        ],
        "chinese_description": [],
        "english_description": [],
        "raw_text": null
    }
]